bytedance_picomocap/__init__.py
bytedance_picomocap-0.0.1.dist-info/METADATA
bytedance_picomocap-0.0.1.dist-info/WHEEL
bytedance_picomocap-0.0.1.dist-info/top_level.txt
bytedance_picomocap-0.0.1.dist-info/RECORD
